flake8_ic/__init__.py
flake8_ic/checker.py
flake8_ic-0.6.0.dist-info/METADATA
flake8_ic-0.6.0.dist-info/WHEEL
flake8_ic-0.6.0.dist-info/entry_points.txt
flake8_ic-0.6.0.dist-info/licenses/LICENSE
flake8_ic-0.6.0.dist-info/RECORD
