Metadata-Version: 2.4
Name: flake8-ic
Version: 0.6.0
Summary: This package provides a plugin for flake8 that checks the usage of ic() function from icecream package.
Author-email: Marco Espinosa <marco@marcoespinosa.com>
License: MIT License
License-File: LICENSE
Keywords: code quality,debugging,flake8,ic,icecream,linting,plugin
Classifier: Development Status :: 4 - Beta
Classifier: Environment :: Console
Classifier: Intended Audience :: Developers
Classifier: License :: OSI Approved :: MIT License
Classifier: Operating System :: OS Independent
Classifier: Programming Language :: Python
Classifier: Programming Language :: Python :: 3
Classifier: Programming Language :: Python :: 3.11
Classifier: Programming Language :: Python :: 3.12
Classifier: Programming Language :: Python :: 3.13
Classifier: Topic :: Software Development :: Libraries :: Python Modules
Classifier: Topic :: Software Development :: Quality Assurance
Classifier: Topic :: Software Development :: Testing
Requires-Python: >=3.11
Requires-Dist: flake8>=7.1.1
Requires-Dist: toml>=0.10.2
